{
    "Dr. Viswanathan V": "50300",
    "Dr. Nithyanandam P": "50443",
    "Dr. Suganya G": "50438",
    "Dr. Sweetlin Hemalatha C": "50767",
    "Dr. Ganesan R": "50338",
    "Dr. Geetha S": "50587",
    "Dr. Janaki Meena M": "50616",
    "Dr. Jeganathan L": "50094",
    "Dr. Lakshmanan K": "54758",
    "Dr. Maheswari N": "50160",
    "Dr. Nayeemulla Khan A": "50161",
    "Dr. Parvathi R": "50186",
    "Dr. Pattabiraman V": "50168",
    "Dr. Subbulakshmi T": "50569",
    "Dr. Asnath Victy Phamila Y": "50590",
    "Dr. Bharadwaja Kumar G": "50319",
    "Dr. Jenila Livingston L M": "50352",
    "Dr. Kumar R": "50304",
    "Dr. Malathi G": "50303",
    "Dr. Neela Narayanan V": "50384",
    "Dr. Nithya Darisini P.S": "50049",
    "Dr. Pradeep Kumar T S": "50024",
    "Dr. Priyadarshini J": "50422",
    "Dr. Rajalakshmi R": "50879",
    "Dr. Renta Chintala Bhargavi": "50577",
    "Dr. Renuka Devi S": "50916",
    "Dr. Saleena B": "50237",
    "Dr. Santhi V": "53398",
    "Dr. Shridevi S": "50266",
    "Dr. Sivabalakrishnan M": "50398",
    "Dr. Srimathi C": "54759",
    "Dr. Umamaheswari E": "64285",
    "Dr. Anusha K": "50930",
    "Dr. B V A N S S Prabhakar Rao": "50276",
    "Dr. Christopher Columbus C": "53035",
    "Dr. Dhanalakshmi R": "52882",
    "Dr. Dinakaran M": "52343",
    "Dr. Ganesh N": "52823",
    "Dr. Harini S": "50159",
    "Dr. Iniya Nehru E": "54128",
    "Dr. Jeya Mala D": "52338",
    "Dr. Karmel A": "50435",
    "Dr. Kumar K": "54834",
    "Dr. Padmavathy T V": "52239",
    "Dr. Parvathy A K": "53627",
    "Dr. Prassanna J": "50417",
    "Dr. Premalatha M": "50289",
    "Dr. Rabindra Kumar Singh": "50391",
    "Dr. Rama Parvathy L": "53154",
    "Dr. RaviChandran M": "54789",
    "Dr. Rekha D": "50359",
    "Dr. Rukmani P": "50154",
    "Dr. Sandhya M": "53050",
    "Dr. Sandhya P": "50410",
    "Dr. Shyamala L": "50918",
    "Dr. Sivagami M": "50007",
    "Dr. Suganya R": "52858",
    "Dr. Abdul Quadir Md": "50386",
    "Dr. Appalaraju Muralidhar": "50178",
    "Dr. Bharathi Raja S": "50299",
    "Dr. Ganala Santoshi": "51679",
    "Dr. Graceline Jasmine S": "50176",
    "Dr. Kanchana Devi V": "50311",
    "Dr. Maheswari S": "50250",
    "Dr. Manjula V": "52278",
    "Dr. Nachiyappan S": "50394",
    "Dr. Nisha V M": "50036",
    "Dr. Poornima S": "54146",
    "Dr. Prakash P": "51682",
    "Dr. Preetha Evangeline D": "54652",
    "Dr. Priyaadharshini M": "50307",
    "Dr. Radha R": "51754",
    "Dr. Rajalakshmi V": "54821",
    "Dr. Rajkumar S": "50301",
    "Dr. Rathna R": "53063",
    "Dr. Sajidha S A": "50063",
    "Dr. Shola Usha Rani": "50432",
    "Dr. Srinivasa Perumal R": "52355",
    "Dr. Thanikachalam V": "53546",
    "Dr. Thomas Abraham J V": "50177",
    "Dr. Tulasi Prasad Sariki": "50389",
    "Dr. Vallidevi K": "52836",
    "Dr. Venkatraman S": "51652",
    "Dr. Vergin Raja Sarobin M": "50138",
    "Dr. Vigneshwari S": "54147",
    "Dr. Vijayalakshmi A": "50270",
    "Dr. Alok Chauhan": "50390",
    "Dr. Anita X": "51662",
    "Dr. Anusooya G": "50408",
    "Dr. Balasundaram A": "51461",
    "Dr. Bhavadharini R M": "52261",
    "Dr. Braveen M": "51327",
    "Dr. Jani Anbarasi L": "51142",
    "Dr. Jayanthi R": "50926",
    "Dr. Jayasudha M": "50322",
    "Dr. Kanniga Devi R": "53080",
    "Dr. Kowsigan M": "54160",
    "Dr. Leninisha S": "51667",
    "Dr. Maria Anu V": "52310",
    "Dr. Menaka Pushpa A": "51656",
    "Dr. Muthumanikandan V": "51328",
    "Dr. Palani Thanaraj K": "53025",
    "Dr. Pradeep K V": "50396",
    "Dr. Prakash B": "50249",
    "Dr. Punitha K": "50401",
    "Dr. Rajakumar R": "53091",
    "Dr. Rajarajeswari S": "50380",
    "Dr. Rajesh Kumar": "50370",
    "Dr. Rajesh M": "50403",
    "Dr. Rama Prabha K P": "52279",
    "Dr. Renuka Devi R": "53159",
    "Dr. Sandeep Kumar Satapathy": "51673",
    "Dr. Saravanan P": "53157",
    "Dr. Sathyarajasekaran K": "50185",
    "Dr. Sivakami R": "53128",
    "Dr. Sobitha Ahila S": "52859",
    "Dr. Sridhar R": "50440",
    "Dr. Umitty Srinivasa Rao": "50201",
    "Dr. Vijayakumar K P": "51743",
    "Dr. Yogesh C": "52353",
    "Dr. Amrit Pal": "51665",
    "Dr. Anandan P": "52337",
    "Dr. Anita Christaline J": "53387",
    "Dr. Arunkumar V": "52277",
    "Dr. Asha Jerlin M": "52350",
    "Dr. Ayesha SK": "51339",
    "Dr. Dharini R": "54775",
    "Dr. Dhivya R": "54827",
    "Dr. Edward Jero S": "51653",
    "Dr. Ilakiyaselvan N": "50183",
    "Dr. Indira B": "53139",
    "Dr. Jayaram B": "50315",
    "Dr. Jothi R": "51458",
    "Dr. Kabilan K": "53126",
    "Dr. Kalaipriyan T": "51946",
    "Dr. Kavitha D": "52209",
    "Dr. Kavitha J C": "53127",
    "Dr. Lekshmi K": "53343",
    "Dr. Malini A": "53899",
    "Dr. Manas Ranjan Prusty": "51457",
    "Dr. Manimegalai T": "52204",
    "Dr. Manju G": "53009",
    "Dr. Pandiyaraju V": "52344",
    "Dr. Parkavi K": "51658",
    "Dr. Pavithra L K": "51657",
    "Dr. Pavithra S": "52883",
    "Dr. Prabhakaran R": "50430",
    "Dr. Pradeep K": "51748",
    "Dr. Prasad M": "51325",
    "Dr. Praveen Joe I R": "52341",
    "Dr. Priyadarshini R": "52200",
    "Dr. Raja M": "53104",
    "Dr. Raja Sree T": "52361",
    "Dr. Rajakumar Arul": "51947",
    "Dr. Rajiv Vincent": "50404",
    "Dr. Rajkumar R": "54527",
    "Dr. Renjith P N": "52288",
    "Dr. Revathi A R": "53049",
    "Dr. Rishikeshan C A": "51672",
    "Dr. Sakthivel V": "51680",
    "Dr. Sankar P": "53601",
    "Dr. Saranyaraj D": "53623",
    "Dr. Saraswathi D": "52342",
    "Dr. Sathian D": "52256",
    "Dr. Sellam V": "53566",
    "Dr. Senthil Kumar A M": "52349",
    "Dr. Sherly A": "52227",
    "Dr. Shivani Gupta": "51659",
    "Dr. Shruti Mishra": "51962",
    "Dr. Sindhu Ravindran": "54510",
    "Dr. Sivakumar P": "52281",
    "Dr. Sridevi S": "53136",
    "Dr. Subbulakshmi P": "51663",
    "Dr. Subitha D": "53124",
    "Dr. Sudha A": "51948",
    "Dr. Suganeshwari G": "51949",
    "Dr. Suguna M": "52215",
    "Dr. Sureshkumar WI": "52304",
    "Dr. Trilok Nath Pandey": "52250",
    "Dr. Uma Maheswari J": "52280",
    "Dr. Vignesh U": "53145",
    "Dr. Abinaya S": "52232",
    "Dr. Abishi Chowdhury": "52194",
    "Dr. Akkarapakkam Suneesh Jacob": "54767",
    "Dr. Amutha Jeevakumari S A": "52273",
    "Dr. Amutha S": "52335",
    "Dr. Anubha Pearline S": "53060",
    "Dr. Aswiga R V": "52291",
    "Dr. Balasaraswathi V R": "53105",
    "Dr. Bhuvaneswari A": "51347",
    "Dr. Brindha S": "52284",
    "Dr. Deepa Nivethika S": "53030",
    "Dr. Devi K": "53617",
    "Dr. Dhavakumar P": "53137",
    "Dr. Dominic Savio M": "52610",
    "Dr. Elakiya E": "53034",
    "Dr. Gayathri Devi S": "53695",
    "Dr. Ilavarasi A K": "51329",
    "Dr. Joshua Sunder David Reddipogu": "53689",
    "Dr. Kaja Mohideen A": "53075",
    "Dr. Krithiga R": "52264",
    "Dr. Kulandai Josephine Julina J": "54785",
    "Dr. Lakshmi Harika Palivela": "53077",
    "Dr. Linda Joseph": "53655",
    "Dr. Maheswari P": "54770",
    "Dr. Malathi D": "53036",
    "Dr. Malini Deepika M": "53048",
    "Dr. Mansoor Hussain D": "52325",
    "Dr. Mercy Rajaselvi Beaulah P": "52262",
    "Dr. Modigari Narendra": "52322",
    "Dr. Monica K M": "52283",
    "Dr. Muthukumaran K": "51651",
    "Dr. Nivedita M": "50318",
    "Dr. Om Kumar C U": "52263",
    "Dr. Padmanaban R": "53103",
    "Dr. Poonkodi M": "53160",
    "Dr. Prem Sankar N": "53161",
    "Dr. Radhika Selvamani B": "51344",
    "Dr. Reena Roy R": "52303",
    "Dr. Revathi M": "52287",
    "Dr. Sahaya Beni Prathiba B": "52245",
    "Dr. Sambath M": "53630",
    "Dr. Sandosh S": "52285",
    "Dr. Sangeetha N": "52334",
    "Dr. Sankari M": "54183",
    "Dr. Sivaramakrishnan N": "53609",
    "Dr. Srisakthi Saravanan": "53046",
    "Dr. Sudheer Kumar E": "53027",
    "Dr. Sujatha M": "54149",
    "Dr. Suseela S": "52266",
    "Dr. Swaminathan A": "51669",
    "Dr. Tamilarasi K": "52247",
    "Dr. Valarmathi K": "53134",
    "Dr. Vatchala S": "52825",
    "Dr. Vidhya Lakshmi M": "53641",
    "Dr. Vijayaraj J": "54799",
    "Dr. Aarthi B": "54151",
    "Dr. Afruza Begum": "53069",
    "Dr. Ahadit A B": "53164",
    "Dr. Aravindkumar S": "53093",
    "Dr. Avuthu Avinash Reddy": "53101",
    "Dr. Balraj E": "53615",
    "Dr. Benil T": "52799",
    "Dr. Benila S": "53608",
    "Dr. Brindha V": "53019",
    "Dr. Deepika Roselind J": "53011",
    "Dr. Hemalatha K": "53624",
    "Dr. Ilavendhan A": "52833",
    "Dr. Indra Priyadharshini S": "52208",
    "Dr. Jai Vinita L": "53626",
    "Dr. Jannath Nisha O S": "53017",
    "Dr. Jeipratha P N": "53629",
    "Dr. Joe Dhanith P R": "52299",
    "Dr. Joshan Athanesious J": "52295",
    "Dr. Kanimozhi S": "53029",
    "Dr. Karthika S K": "53888",
    "Dr. Karthikeyan N": "53112",
    "Dr. Kavipriya G": "53388",
    "Dr. Kiruthika S": "52312",
    "Dr. Kishor Kisan Ingle": "53153",
    "Dr. Kumaran K": "53610",
    "Dr. Manikandan P": "53619",
    "Dr. Marimuthu M": "53166",
    "Dr. Mary Shamala L": "52346",
    "Dr. Meignanamoorthi D": "54786",
    "Dr. Natarajan B": "53393",
    "Dr. Noel Jeygar Robert V": "52275",
    "Dr. Omana J": "53638",
    "Dr. Padma J": "53408",
    "Dr. Prabha B": "53558",
    "Dr. Pravin Renold A": "52889",
    "Dr. Premanand V": "53078",
    "Dr. Prethija G": "53694",
    "Dr. Radhika R": "54680",
    "Dr. Rajesh R": "52879",
    "Dr. Ranjith R": "54828",
    "Dr. Rolla Subrahmanyam": "53552",
    "Dr. Sakthivel R": "53663",
    "Dr. Saranya G": "53637",
    "Dr. Saranya M": "54783",
    "Dr.Sendhil R": "52777",
    "Dr. Senthil Prakash P N": "53073",
    "Dr. Sharmila Devi S": "53545",
    "Dr. Siva Priya M S": "53645",
    "Dr. Sivaranjani N": "53900",
    "Dr. Smrithy G S": "52309",
    "Dr. Sreeja P S": "53382",
    "Dr. Sudha C": "53685",
    "Dr. Sudharson S": "53074",
    "Dr. Suhail K": "54508",
    "Dr. Sujithra @ Kanmani R": "52835",
    "Dr. Suvidha Rupesh Kumar": "53039",
    "Dr. Uma Maheswari K": "53674",
    "Dr. Umesh K": "53877",
    "Dr. Valarmathi P": "52192",
    "Dr. Vasanthakumar S": "54830",
    "Dr. Vijayaprabakaran K": "52792",
    "Dr. Vivekanandan M": "53646",
    "Dr. Selvam D": "53391",
    "Dr. Jahangeer Sidiq S": "52851",
    "Dr. Sarita Kumari": "53642",
    "Dr. Helen Vijitha P": "53616",
    "Dr. Kshma Trivedi": "53647",
    "Dr. Madura Meenakshi R": "53696",
    "Dr. Softya Sebastian": "53568",
    "Dr. Tahir Mujtaba": "53598",
    "Prof. Khadar Nawas K": "50239",
    "Dr. Elakya R": "54173",
    "Dr. Karthika V": "53076",
    "Dr. Logeswari G": "53368",
    "Dr. Shree Prakash": "53567",
    "Prof. Johanan Joysingh S": "53661",
    "Prof. Balaji V": "53396",
    "Prof. Berin Shalu S": "51850",
    "Prof. Deepika R": "52874",
    "Prof. Hemila Rexline D": "53692",
    "Prof. Jeyamani D": "53560",
    "Prof. Logeshwari V": "53693",
    "Prof. Johnsi R": "53392",
    "Prof. Manoranjitham M": "52792",
    "Prof. Pankaja Lakshmi P": "51605",
    "Prof. Priyanka Mishra": "53162",
    "Prof. Ramesh Kannan R": "52872",
    "Prof. Sheela Lavanya J M": "52628",
    "Mr. Bezaleel S": "53816",
    "Mr. Haris R": "53864",
    "Mr. Kishore Kumar G S": "53863",
    "Mr. Prem Kumar E": "53433",
    "Mr. Ranjith J": "52408",
    "Ms. Aswini H": "53501",
    "Ms. Divya S": "53760",
    "Ms. Jenifa Sharon J": "53244",
    "Ms. Keerthana G": "53827",
    "Ms. Mahalakshmi G": "53183",
    "Ms. Manicka Prabha M": "53458",
    "Ms. Narmadha R": "53494",
    "Ms. Niranjana Junar": "53175",
    "Ms. Preethi M": "53337",
    "Ms. Priyadharshini S": "53450",
    "Ms. Priyanka S": "53247",
    "Ms. Saranya M": "53427",
    "Ms. Selvalakshmi A": "53260",
    "Ms. Sruthi C K": "53250",
    "Ms. Sujatha M": "53445",
    "Ms. Sumathy R": "53480",
    "Ms. Suruthi M": "53211",
    "Ms. Vijaya Lakshmi N": "53717",
    "Ms. Yashika P": "53266"
}